smartpy/__init__.py
smartpy/inout.py
smartpy/objfunctions.py
smartpy/parameters.py
smartpy/smart.py
smartpy/structure.py
smartpy/timeframe.py
smartpy/version.py
smartpy/montecarlo/__init__.py
smartpy/montecarlo/best.py
smartpy/montecarlo/glue.py
smartpy/montecarlo/lhs.py
smartpy/montecarlo/montecarlo.py
smartpy/montecarlo/total.py
smartpy-0.2.2.dist-info/LICENCE.rst
smartpy-0.2.2.dist-info/METADATA
smartpy-0.2.2.dist-info/WHEEL
smartpy-0.2.2.dist-info/top_level.txt
smartpy-0.2.2.dist-info/RECORD
