Metadata-Version: 2.1
Name: smartpy
Version: 0.2.2
Summary: An implementation of the rainfall-runoff model SMART in Python
Download-URL: https://pypi.python.org/pypi/smartpy
Author: Thibault Hallouin, Eva Mockler, and Michael Bruen
Author-email: thibhlln@gmail.com
License: GPL-3.0
Project-URL: Bug Tracker, https://github.com/thibhlln/smartpy/issues
Project-URL: User Support, https://github.com/thibhlln/smartpy/discussions
Project-URL: Documentation, https://thibhlln.github.io/smartpy
Project-URL: Source Code, https://github.com/thibhlln/smartpy
Platform: UNKNOWN
Classifier: Development Status :: 4 - Beta
Classifier: Natural Language :: English
Classifier: Intended Audience :: Science/Research
Classifier: Topic :: Scientific/Engineering :: Hydrology
Classifier: Operating System :: MacOS
Classifier: Operating System :: Microsoft :: Windows
Classifier: Operating System :: POSIX :: Linux
Classifier: License :: OSI Approved :: GNU General Public License v3 (GPLv3)
Classifier: Programming Language :: Python :: 3.7
Classifier: Programming Language :: Python :: 3.8
Classifier: Programming Language :: Python :: 3.9
Provides-Extra: with_netcdf
Provides-Extra: with_spotpy
Provides-Extra: with_smartcpp
Provides-Extra: with_all_extras
License-File: LICENCE.rst
